dataprob/__init__.py
dataprob/__version__.py
dataprob/fitters/__init__.py
dataprob/fitters/base.py
dataprob/fitters/bootstrap.py
dataprob/fitters/ml.py
dataprob/fitters/setup.py
dataprob/fitters/bayesian/__init__.py
dataprob/fitters/bayesian/_prior_processing.py
dataprob/fitters/bayesian/bayesian_sampler.py
dataprob/model_wrapper/__init__.py
dataprob/model_wrapper/_dataframe_processing.py
dataprob/model_wrapper/_function_processing.py
dataprob/model_wrapper/model_wrapper.py
dataprob/model_wrapper/vector_model_wrapper.py
dataprob/model_wrapper/wrap_function.py
dataprob/plot/__init__.py
dataprob/plot/_plot_utils.py
dataprob/plot/appearance.py
dataprob/plot/plot_corner.py
dataprob/plot/plot_fit.py
dataprob/plot/plot_residuals.py
dataprob/plot/plot_residuals_hist.py
dataprob/plot/plot_summary.py
dataprob/util/__init__.py
dataprob/util/check.py
dataprob/util/get_fit_quality.py
dataprob/util/read_spreadsheet.py
dataprob/util/stats.py
dataprob-0.9.4.dist-info/LICENSE
dataprob-0.9.4.dist-info/METADATA
dataprob-0.9.4.dist-info/WHEEL
dataprob-0.9.4.dist-info/top_level.txt
dataprob-0.9.4.dist-info/RECORD
