Metadata-Version: 2.1
Name: dataprob
Version: 0.9.4
Summary: Do likelihood based parameter estimation using maximum likeihood and bayesian methods
Author-email: Mike Harms <harms@uoregon.edu>
Maintainer-email: Mike Harms <harms@uoregon.edu>
License: Copyright (c) 2020 Michael J. Harms.  
Project-URL: Repository, https://github.com/harmslab/dataprob.git
Project-URL: Bug Tracker, https://github.com/harmslab/dataprob/issues
Keywords: likelihood,maximum likelihood,ML,Bayesian,MCMC,monte carlo,regression,estimator
Classifier: Development Status :: 5 - Production/Stable
Classifier: Programming Language :: Python
Requires-Python: >=3.10
License-File: LICENSE
Requires-Dist: numpy
Requires-Dist: pandas
Requires-Dist: openpyxl
Requires-Dist: matplotlib
Requires-Dist: scipy
Requires-Dist: emcee
Requires-Dist: corner
Requires-Dist: tqdm
Provides-Extra: docs
Requires-Dist: pydata-sphinx-theme ; extra == 'docs'
Provides-Extra: test
Requires-Dist: coverage ; extra == 'test'
Requires-Dist: flake8 ; extra == 'test'
Requires-Dist: pytest ; extra == 'test'
Requires-Dist: genbadge ; extra == 'test'
